logstash_async/__init__.py
logstash_async/constants.py
logstash_async/formatter.py
logstash_async/handler.py
logstash_async/transport.py
logstash_async/utils.py
logstash_async/worker.py
python_logstash_async_dwn-1.0.0.dist-info/DESCRIPTION.rst
python_logstash_async_dwn-1.0.0.dist-info/METADATA
python_logstash_async_dwn-1.0.0.dist-info/RECORD
python_logstash_async_dwn-1.0.0.dist-info/WHEEL
python_logstash_async_dwn-1.0.0.dist-info/metadata.json
python_logstash_async_dwn-1.0.0.dist-info/top_level.txt
