Metadata-Version: 2.0
Name: python-logstash-async-dwn
Version: 1.0.0
Summary: Asynchronous Python logging handler for Logstash.
Home-page: https://github.com/davidwneary/python-logstash-async
Author: David Neary
Author-email: UNKNOWN
License: MIT
Keywords: logging logstash asynchronous
Platform: UNKNOWN
Classifier: Development Status :: 4 - Beta
Classifier: Intended Audience :: Developers
Classifier: License :: OSI Approved :: MIT License
Classifier: Operating System :: OS Independent
Classifier: Programming Language :: Python
Classifier: Programming Language :: Python :: 2
Classifier: Programming Language :: Python :: 3
Classifier: Topic :: Internet :: WWW/HTTP
Classifier: Topic :: Software Development :: Libraries :: Python Modules
Classifier: Topic :: System :: Logging
Requires-Dist: six
